{"name":"JFrog","postlist":[{"title":"初识 JFrog Artifactory","slug":"2019/11/artifactory-install-and-upgrade","date":"2019-11-10T09:52:58.000Z","updated":"2024-04-28T15:43:38.249Z","comments":true,"path":"api/articles/2019/11/artifactory-install-and-upgrade.json","excerpt":null,"keywords":null,"cover":"/2019/11/artifactory-install-and-upgrade/homepage.png","content":null,"raw":null,"categories":[{"name":"JFrog","path":"api/categories/JFrog.json"}],"tags":[{"name":"Artifactory","path":"api/tags/Artifactory.json"},{"name":"JFrog","path":"api/tags/JFrog.json"}]},{"title":"解决 Jenkins Artifactory Plugin 仅在 AIX 上传制品到 https 协议的 Artifactory 失败的问题","slug":"2020/06/java-net-socketexception-on-aix","date":"2020-06-03T11:30:03.000Z","updated":"2024-04-28T15:43:38.269Z","comments":true,"path":"api/articles/2020/06/java-net-socketexception-on-aix.json","excerpt":null,"keywords":null,"cover":"/2020/06/java-net-socketexception-on-aix/configure-agent-environment-variable.png","content":null,"raw":null,"categories":[{"name":"Jenkins","path":"api/categories/Jenkins.json"}],"tags":[{"name":"Troubleshooting","path":"api/tags/Troubleshooting.json"},{"name":"Artifactory","path":"api/tags/Artifactory.json"},{"name":"JFrog","path":"api/tags/JFrog.json"}]},{"title":"写给那些想使用 JFrog Artifactory 管理制品的人","slug":"2020/10/what-is-artifactory","date":"2020-10-04T12:43:46.000Z","updated":"2024-04-28T15:43:38.277Z","comments":true,"path":"api/articles/2020/10/what-is-artifactory.json","excerpt":null,"keywords":null,"cover":"/2020/10/what-is-artifactory/support-package-formats.png","content":null,"raw":null,"categories":[{"name":"JFrog","path":"api/categories/JFrog.json"}],"tags":[{"name":"Artifactory","path":"api/tags/Artifactory.json"},{"name":"JFrog","path":"api/tags/JFrog.json"}]},{"title":"How to download the entire folder artifacts when Artifactory \"Download Folder functionality is disabled\"?","slug":"2021/05/artifactory-api-search","date":"2021-05-04T06:37:00.000Z","updated":"2024-04-28T15:43:38.285Z","comments":true,"path":"api/articles/2021/05/artifactory-api-search.json","excerpt":null,"keywords":null,"cover":"/2021/05/artifactory-api-search/pattern-search.png","content":null,"raw":null,"categories":[{"name":"JFrog","path":"api/categories/JFrog.json"}],"tags":[{"name":"Artifactory","path":"api/tags/Artifactory.json"},{"name":"JFrog","path":"api/tags/JFrog.json"}]}]}