{"name":"VirtualBox","postlist":[{"title":"用 VirtualBox 配置一台 Linux 虚拟机","slug":"2020/02/Setup-Linux-in-VirtualBox","date":"2020-02-08T03:25:48.000Z","updated":"2023-03-01T14:21:26.683Z","comments":true,"path":"api/articles/2020/02/Setup-Linux-in-VirtualBox.json","excerpt":null,"keywords":null,"cover":null,"content":null,"raw":null,"categories":[{"name":"OS","path":"api/categories/OS.json"}],"tags":[{"name":"Linux","path":"api/tags/Linux.json"},{"name":"VirtualBox","path":"api/tags/VirtualBox.json"}]},{"title":"Vagrant 和 Docker 的区别，该如何选？","slug":"2022/01/vagrant-vs-docker","date":"2022-02-14T00:30:00.000Z","updated":"2023-03-01T14:21:26.727Z","comments":true,"path":"api/articles/2022/01/vagrant-vs-docker.json","excerpt":null,"keywords":null,"cover":"/2022/01/vagrant-vs-docker/host.jpg","content":null,"raw":null,"categories":[{"name":"Vagrant","path":"api/categories/Vagrant.json"}],"tags":[{"name":"Docker","path":"api/tags/Docker.json"},{"name":"VirtualBox","path":"api/tags/VirtualBox.json"},{"name":"Vagrant","path":"api/tags/Vagrant.json"}]},{"title":"什么是 Vagrant? Vagrant 和 VirtualBox 的区别","slug":"2022/01/vagrant","date":"2022-02-11T00:30:00.000Z","updated":"2023-03-01T14:21:26.727Z","comments":true,"path":"api/articles/2022/01/vagrant.json","excerpt":null,"keywords":null,"cover":"/2022/01/vagrant/vagrant_virtualbox.png","content":null,"raw":null,"categories":[{"name":"Vagrant","path":"api/categories/Vagrant.json"}],"tags":[{"name":"VirtualBox","path":"api/tags/VirtualBox.json"},{"name":"Vagrant","path":"api/tags/Vagrant.json"}]}]}