{"title":"Nightwatch 元素判断","slug":"2017/12/nightwatch-element-check","date":"2017-12-14T09:34:18.000Z","updated":"2023-10-08T12:01:27.247Z","comments":true,"path":"api/articles/2017/12/nightwatch-element-check.json","excerpt":null,"covers":null,"content":"<h3 id=\"Nightwatch-元素常用验证方法\"><a href=\"#Nightwatch-元素常用验证方法\" class=\"headerlink\" title=\"Nightwatch 元素常用验证方法\"></a>Nightwatch 元素常用验证方法</h3><p>验证元素的值信息</p>\n<figure class=\"highlight javascript\"><table><tr><td class=\"code\"><pre><span class=\"line\">andesFormSection</span><br><span class=\"line\">    .<span class=\"property\">assert</span>.<span class=\"title function_\">containsText</span>(<span class=\"string\">&#x27;@errorMessage&#x27;</span>, <span class=\"string\">&#x27;The email address is invalid.&#x27;</span>)</span><br></pre></td></tr></table></figure>\n\n<p>验证元素是否可用</p>\n<figure class=\"highlight javascript\"><table><tr><td class=\"code\"><pre><span class=\"line\">andesFormSection</span><br><span class=\"line\">    .<span class=\"property\">assert</span>.<span class=\"title function_\">attributeEquals</span>(<span class=\"string\">&#x27;@continueBtn&#x27;</span>, <span class=\"string\">&#x27;disabled&#x27;</span>, <span class=\"string\">&#x27;true&#x27;</span>);</span><br></pre></td></tr></table></figure>\n\n<p>等待元素可用</p>\n<figure class=\"highlight javascript\"><table><tr><td class=\"code\"><pre><span class=\"line\">andesFormSection</span><br><span class=\"line\">    .<span class=\"property\">expect</span>.<span class=\"title function_\">element</span>(<span class=\"string\">&#x27;@signInBtn&#x27;</span>).<span class=\"property\">to</span>.<span class=\"property\">be</span>.<span class=\"property\">visible</span>.<span class=\"title function_\">before</span>(<span class=\"number\">5000</span>);</span><br><span class=\"line\"></span><br><span class=\"line\">或者</span><br><span class=\"line\"></span><br><span class=\"line\">andesFormSection</span><br><span class=\"line\">    <span class=\"title function_\">waitForElementVisible</span>(<span class=\"string\">&#x27;signInBtn&#x27;</span>, <span class=\"number\">5000</span>);</span><br></pre></td></tr></table></figure>\n\n<p>等待元素呈现</p>\n<figure class=\"highlight javascript\"><table><tr><td class=\"code\"><pre><span class=\"line\">andesFormSection</span><br><span class=\"line\">    .<span class=\"property\">expect</span>.<span class=\"title function_\">element</span>(<span class=\"string\">&#x27;@signInBtn&#x27;</span>).<span class=\"property\">to</span>.<span class=\"property\">be</span>.<span class=\"property\">present</span>.<span class=\"title function_\">before</span>(<span class=\"number\">5000</span>);</span><br><span class=\"line\"></span><br><span class=\"line\">或者</span><br><span class=\"line\"></span><br><span class=\"line\">andesFormSection</span><br><span class=\"line\">    <span class=\"title function_\">waitForElementPresent</span>(<span class=\"string\">&#x27;signInBtn&#x27;</span>, <span class=\"number\">5000</span>);</span><br></pre></td></tr></table></figure>\n","more":"<h3 id=\"Nightwatch-元素常用验证方法\"><a href=\"#Nightwatch-元素常用验证方法\" class=\"headerlink\" title=\"Nightwatch 元素常用验证方法\"></a>Nightwatch 元素常用验证方法</h3><p>验证元素的值信息</p>\n<figure class=\"highlight javascript\"><table><tr><td class=\"code\"><pre><span class=\"line\">andesFormSection</span><br><span class=\"line\">    .<span class=\"property\">assert</span>.<span class=\"title function_\">containsText</span>(<span class=\"string\">&#x27;@errorMessage&#x27;</span>, <span class=\"string\">&#x27;The email address is invalid.&#x27;</span>)</span><br></pre></td></tr></table></figure>\n\n<p>验证元素是否可用</p>\n<figure class=\"highlight javascript\"><table><tr><td class=\"code\"><pre><span class=\"line\">andesFormSection</span><br><span class=\"line\">    .<span class=\"property\">assert</span>.<span class=\"title function_\">attributeEquals</span>(<span class=\"string\">&#x27;@continueBtn&#x27;</span>, <span class=\"string\">&#x27;disabled&#x27;</span>, <span class=\"string\">&#x27;true&#x27;</span>);</span><br></pre></td></tr></table></figure>\n\n<p>等待元素可用</p>\n<figure class=\"highlight javascript\"><table><tr><td class=\"code\"><pre><span class=\"line\">andesFormSection</span><br><span class=\"line\">    .<span class=\"property\">expect</span>.<span class=\"title function_\">element</span>(<span class=\"string\">&#x27;@signInBtn&#x27;</span>).<span class=\"property\">to</span>.<span class=\"property\">be</span>.<span class=\"property\">visible</span>.<span class=\"title function_\">before</span>(<span class=\"number\">5000</span>);</span><br><span class=\"line\"></span><br><span class=\"line\">或者</span><br><span class=\"line\"></span><br><span class=\"line\">andesFormSection</span><br><span class=\"line\">    <span class=\"title function_\">waitForElementVisible</span>(<span class=\"string\">&#x27;signInBtn&#x27;</span>, <span class=\"number\">5000</span>);</span><br></pre></td></tr></table></figure>\n\n<p>等待元素呈现</p>\n<figure class=\"highlight javascript\"><table><tr><td class=\"code\"><pre><span class=\"line\">andesFormSection</span><br><span class=\"line\">    .<span class=\"property\">expect</span>.<span class=\"title function_\">element</span>(<span class=\"string\">&#x27;@signInBtn&#x27;</span>).<span class=\"property\">to</span>.<span class=\"property\">be</span>.<span class=\"property\">present</span>.<span class=\"title function_\">before</span>(<span class=\"number\">5000</span>);</span><br><span class=\"line\"></span><br><span class=\"line\">或者</span><br><span class=\"line\"></span><br><span class=\"line\">andesFormSection</span><br><span class=\"line\">    <span class=\"title function_\">waitForElementPresent</span>(<span class=\"string\">&#x27;signInBtn&#x27;</span>, <span class=\"number\">5000</span>);</span><br></pre></td></tr></table></figure>\n","categories":[{"name":"Automation","path":"api/categories/Automation.json"}],"tags":[{"name":"Nightwatch","path":"api/tags/Nightwatch.json"},{"name":"Automation","path":"api/tags/Automation.json"}]}